ir_datasets_clueweb22/__init__.py
ir_datasets_clueweb22/__main__.py
ir_datasets_clueweb22/bibliography.bib
ir_datasets_clueweb22/clueweb22.py
ir_datasets_clueweb22/clueweb22.yaml
ir_datasets_clueweb22/conftest.py
ir_datasets_clueweb22/downloads.json
ir_datasets_clueweb22/io.py
ir_datasets_clueweb22/metadata.json
ir_datasets_clueweb22/test_clueweb22.py
ir_datasets_clueweb22/test_io.py
ir_datasets_clueweb22/util.py
ir_datasets_clueweb22-0.1.0.dist-info/LICENSE
ir_datasets_clueweb22-0.1.0.dist-info/METADATA
ir_datasets_clueweb22-0.1.0.dist-info/WHEEL
ir_datasets_clueweb22-0.1.0.dist-info/entry_points.txt
ir_datasets_clueweb22-0.1.0.dist-info/top_level.txt
ir_datasets_clueweb22-0.1.0.dist-info/RECORD
