Metadata-Version: 2.1
Name: ir-datasets-clueweb22
Version: 0.1.0
Summary: Extension for accessing the ClueWeb22 via ir_datasets.
Author-email: Jan Heinrich Reimer <heinrich.reimer@uni-jena.de>
Project-URL: Homepage, https://github.com/heinrichreimer/ir-datasets-clueweb22
Project-URL: Bug Tracker, https://github.com/heinrichreimer/ir-datasets-clueweb22/issues
Classifier: Programming Language :: Python :: 3
Classifier: Programming Language :: Python :: 3 :: Only
Classifier: Programming Language :: Python :: 3.10
Classifier: Programming Language :: Python :: 3.11
Classifier: License :: OSI Approved :: MIT License
Classifier: Operating System :: OS Independent
Classifier: Intended Audience :: Science/Research
Classifier: Topic :: Scientific/Engineering
Requires-Python: >=3.10
License-File: LICENSE
Requires-Dist: fastwarc ~=0.14.0
Requires-Dist: importlib-metadata ~=7.0
Requires-Dist: ir-datasets ~=0.5.6
Requires-Dist: pyyaml ~=6.0
Requires-Dist: typing-extensions ~=4.11
Provides-Extra: tests
Requires-Dist: bandit[toml] ~=1.7 ; extra == 'tests'
Requires-Dist: mypy ~=1.5 ; extra == 'tests'
Requires-Dist: pytest ~=8.0 ; extra == 'tests'
Requires-Dist: pytest-cov ~=5.0 ; extra == 'tests'
Requires-Dist: pytest-subtests ~=0.12.1 ; extra == 'tests'
Requires-Dist: ruff ~=0.3.0 ; extra == 'tests'
Requires-Dist: types-pyyaml ~=6.0 ; extra == 'tests'
